{
  "api_name": "api_datalab_search",
  "result": "PASS",
  "response": {
    "errMsg": "TypeError: .startDate -> should be string\n.startDate -> should be string\n.startDate -> should match some schema in anyOf",
    "errId": "2024-12-11T02:50:46+09:00/463232964-70968412",
    "body": "{\"startDate\":null,\"endDate\":\"2016-01-01\",\"timeUnit\":\"date\",\"keywordGroups\":[{\"groupName\":\"ABC\",\"keywords\":[\"A\",\"B\",\"C\",\"D\",\"E\",\"F\",\"G\",\"H\",\"I\",\"J\",\"K\",\"L\",\"M\",\"N\",\"O\",\"P\",\"Q\",\"R\",\"S\",\"T\"]}]}"
  },
  "parameter": {
    "startDate": null,
    "endDate": "2016-01-01",
    "timeUnit": "date",
    "keywordGroups": [
      {
        "groupName": "ABC",
        "keywords": [
          "A",
          "B",
          "C",
          "D",
          "E",
          "F",
          "G",
          "H",
          "I",
          "J",
          "K",
          "L",
          "M",
          "N",
          "O",
          "P",
          "Q",
          "R",
          "S",
          "T"
        ]
      }
    ]
  }
}